galmorph/__init__.py
galmorph/core.py
galmorph/data_conversion.py
galmorph-1.0.2.dist-info/licenses/LICENSE
galmorph-1.0.2.dist-info/METADATA
galmorph-1.0.2.dist-info/WHEEL
galmorph-1.0.2.dist-info/top_level.txt
galmorph-1.0.2.dist-info/RECORD
