Metadata-Version: 2.4
Name: galmorph
Version: 1.0.2
Summary: Galaxy morphology analysis tool
Author: Priyatam Kumar, Mitali Damle
Author-email: Shahd Moghazy <shahdmoghazy17@gmail.com>
License: MIT
License-File: LICENSE
Requires-Dist: numpy
Requires-Dist: matplotlib
Dynamic: license-file
